cloud_init_models/__init__.py
cloud_init_models/apt_configure.py
cloud_init_models/ca_certs.py
cloud_init_models/ubuntu_pro.py
cloud_init_models/users_groups.py
cloud_init_models-0.2.0.dist-info/licenses/LICENSE
cloud_init_models-0.2.0.dist-info/METADATA
cloud_init_models-0.2.0.dist-info/WHEEL
cloud_init_models-0.2.0.dist-info/top_level.txt
cloud_init_models-0.2.0.dist-info/RECORD
