Metadata-Version: 2.4
Name: cloud-init-models
Version: 0.2.0
Summary: cloud-init TypedDict models autogenerated from datamodel-code-generator
Author-email: jealouscloud <github@noaha.org>
Project-URL: Homepage, https://github.com/jealouscloud/cloud-init-models
Project-URL: Repository, https://github.com/jealouscloud/cloud-init-models
Classifier: Development Status :: 3 - Alpha
Classifier: Intended Audience :: Developers
Classifier: Programming Language :: Python :: 3.9
Classifier: Programming Language :: Python :: 3.10
Classifier: Programming Language :: Python :: 3.11
Classifier: Programming Language :: Python :: 3.12
Requires-Python: >=3.9
License-File: LICENSE
Requires-Dist: datamodel-code-generator>=0.35.0
Requires-Dist: typing-extensions>=4.13.2
Dynamic: license-file
